rezipe/__about__.py
rezipe/__init__.py
rezipe/goods.py
rezipe/ingredient.py
rezipe/mix.py
rezipe/pint_currency.txt
rezipe/treatment.py
rezipe/unit.py
rezipe/utils_jupyter.py
rezipe-0.2.0.dist-info/LICENSE
rezipe-0.2.0.dist-info/METADATA
rezipe-0.2.0.dist-info/WHEEL
rezipe-0.2.0.dist-info/RECORD
